{
  "type": "fulltime",
  "summary": "韩国 2-1 捷克",
  "analysis": "全场比赛结束，韩国 2-1 战胜捷克。\n\n进球回顾：第59分钟Ladislav Krejcí Goal - Header为捷克进球；第67分钟Hwang In-Beom Goal为韩国进球；第80分钟Oh Hyeon-Gyu Goal为韩国进球。\n\n韩国在进攻端创造了更多威胁，结果与场面相符。\n\n韩国控球率 62%，占据一定控球优势。\n\n下半场第59分钟Ladislav Krejcí Goal - Header的进球成为比赛关键转折。",
  "key_stats": [
    "控球率：韩国 62% - 38% 捷克",
    "射门：韩国 15次（6次射正） - 捷克 7次（4次射正）",
    "角球：韩国 4 - 5 捷克",
    "比分：韩国 2 - 1 捷克"
  ],
  "momentum": "主队稍占上风",
  "star_performers": [
    "Ladislav Krejcí Goal - Header",
    "Hwang In-Beom Goal",
    "Oh Hyeon-Gyu Goal",
    "Lee Gi-Hyuk Yellow Card"
  ]
}